esp_batch_uploader/__init__.py
esp_batch_uploader/__main__.py
esp_batch_uploader/config.py
esp_batch_uploader/logger.py
esp_batch_uploader/uploader/__init__.py
esp_batch_uploader/uploader/batch_manager.py
esp_batch_uploader/uploader/discovery.py
esp_batch_uploader/uploader/upload_client.py
esp_batch_uploader/uploader/upload_runner.py
esp_batch_uploader-1.0.4.dist-info/METADATA
esp_batch_uploader-1.0.4.dist-info/WHEEL
esp_batch_uploader-1.0.4.dist-info/entry_points.txt
esp_batch_uploader-1.0.4.dist-info/top_level.txt
esp_batch_uploader-1.0.4.dist-info/RECORD
