Metadata-Version: 2.4
Name: esp-batch-uploader
Version: 1.0.4
Summary: Batch file uploader to ESP32 devices over HTTP with UDP discovery
Author: Abdullah Bajwa
Classifier: Programming Language :: Python :: 3
Classifier: Operating System :: OS Independent
Requires-Python: >=3.7
Requires-Dist: aiohttp
Dynamic: author
Dynamic: classifier
Dynamic: requires-dist
Dynamic: requires-python
Dynamic: summary
